s3_file_field/__init__.py
s3_file_field/_multipart.py
s3_file_field/_multipart_minio.py
s3_file_field/_multipart_s3.py
s3_file_field/_registry.py
s3_file_field/_sizes.py
s3_file_field/apps.py
s3_file_field/checks.py
s3_file_field/fields.py
s3_file_field/fixtures.py
s3_file_field/forms.py
s3_file_field/py.typed
s3_file_field/rest_framework.py
s3_file_field/signals.py
s3_file_field/urls.py
s3_file_field/views.py
s3_file_field/widgets.py
s3_file_field/static/s3_file_field/widget.css
s3_file_field/static/s3_file_field/widget.js
django_s3_file_field-1.1.0.dist-info/METADATA
django_s3_file_field-1.1.0.dist-info/WHEEL
django_s3_file_field-1.1.0.dist-info/entry_points.txt
django_s3_file_field-1.1.0.dist-info/licenses/LICENSE
django_s3_file_field-1.1.0.dist-info/RECORD
