Metadata-Version: 2.4
Name: django-s3-file-field
Version: 1.1.0
Summary: A Django library for uploading files directly to AWS S3 or MinIO Storage from HTTP clients.
Project-URL: Repository, https://github.com/kitware-resonant/django-s3-file-field
Project-URL: Bug Reports, https://github.com/kitware-resonant/django-s3-file-field/issues
Maintainer-email: "Kitware, Inc." <kitware@kitware.com>
License-Expression: Apache-2.0
License-File: LICENSE
Keywords: django,django-widget,kitware-resonant,minio,resonant,s3
Classifier: Development Status :: 5 - Production/Stable
Classifier: Environment :: Web Environment
Classifier: Framework :: Django
Classifier: Framework :: Django :: 4
Classifier: Framework :: Django :: 4.2
Classifier: Framework :: Django :: 5
Classifier: Framework :: Django :: 5.1
Classifier: Framework :: Django :: 5.2
Classifier: Intended Audience :: Developers
Classifier: Operating System :: OS Independent
Classifier: Programming Language :: Python
Classifier: Programming Language :: Python :: 3
Classifier: Programming Language :: Python :: 3.10
Classifier: Programming Language :: Python :: 3.11
Classifier: Programming Language :: Python :: 3.12
Classifier: Programming Language :: Python :: 3.13
Requires-Python: >=3.10
Requires-Dist: django>=4.2
Requires-Dist: djangorestframework
Provides-Extra: minio
Requires-Dist: django-minio-storage>=0.5; extra == 'minio'
Requires-Dist: minio>=7; extra == 'minio'
Provides-Extra: pytest
Requires-Dist: pytest; extra == 'pytest'
Provides-Extra: s3
Requires-Dist: boto3; extra == 's3'
Requires-Dist: django-storages[s3]>=1.14; extra == 's3'
